{"NumFixedViewers": 4, "TimeElapsed": 237.5062539577484, "WorldStates": [{"BuilderInventory": [{"Index": 0, "Type": "cwcmod:cwc_yellow_rn", "Quantity": 20}, {"Index": 1, "Type": "cwcmod:cwc_red_rn", "Quantity": 20}, {"Index": 2, "Type": "cwcmod:cwc_green_rn", "Quantity": 20}, {"Index": 3, "Type": "cwcmod:cwc_orange_rn", "Quantity": 20}, {"Index": 4, "Type": "cwcmod:cwc_purple_rn", "Quantity": 20}, {"Index": 5, "Type": "cwcmod:cwc_blue_rn", "Quantity": 20}], "ChatHistoryTokenized": [["<Builder>", "mission", "has", "started", "."]], "Timestamp": "2018-04-16 20:37:20", "ScreenshotPath": "0-Builder-chat.png", "BlocksInGrid": [], "BuilderPosition": {"X": 0.0, "Y": 1.0, "Z": 0.0, "Yaw": 0.0, "Pitch": 0.0}}, {"BuilderInventory": [{"Index": 0, "Type": "cwcmod:cwc_yellow_rn", "Quantity": 20}, {"Index": 1, "Type": "cwcmod:cwc_red_rn", "Quantity": 20}, {"Index": 2, "Type": "cwcmod:cwc_green_rn", "Quantity": 20}, {"Index": 3, "Type": "cwcmod:cwc_orange_rn", "Quantity": 20}, {"Index": 4, "Type": "cwcmod:cwc_purple_rn", "Quantity": 20}, {"Index": 5, "Type": "cwcmod:cwc_blue_rn", "Quantity": 20}], "ChatHistoryTokenized": [["<Builder>", "mission", "has", "started", "."], ["<Builder>", "rip", "me", "lol"]], "Timestamp": "2018-04-16 20:37:21", "ScreenshotPath": "1683-Builder-chat.png", "BlocksInGrid": [], "BuilderPosition": {"X": 0.0, "Y": 1.0, "Z": 0.0, "Yaw": 0.0, "Pitch": 0.0}}, {"BuilderInventory": [{"Index": 0, "Type": "cwcmod:cwc_yellow_rn", "Quantity": 20}, {"Index": 1, "Type": "cwcmod:cwc_red_rn", "Quantity": 20}, {"Index": 2, "Type": "cwcmod:cwc_green_rn", "Quantity": 20}, {"Index": 3, "Type": "cwcmod:cwc_orange_rn", "Quantity": 20}, {"Index": 4, "Type": "cwcmod:cwc_purple_rn", "Quantity": 20}, {"Index": 5, "Type": "cwcmod:cwc_blue_rn", "Quantity": 20}], "ChatHistoryTokenized": [["<Builder>", "mission", "has", "started", "."], ["<Builder>", "rip", "me", "lol"], ["<Architect>", "now", "with", "blue", "blocks"]], "Timestamp": "2018-04-16 20:37:30", "ScreenshotPath": "9998-Builder-chat.png", "BlocksInGrid": [], "BuilderPosition": {"X": 0.0, "Y": 1.0, "Z": 0.0, "Yaw": -112.34998, "Pitch": 76.19997}}, {"BuilderInventory": [{"Index": 0, "Type": "cwcmod:cwc_yellow_rn", "Quantity": 20}, {"Index": 1, "Type": "cwcmod:cwc_red_rn", "Quantity": 20}, {"Index": 2, "Type": "cwcmod:cwc_green_rn", "Quantity": 20}, {"Index": 3, "Type": "cwcmod:cwc_orange_rn", "Quantity": 20}, {"Index": 4, "Type": "cwcmod:cwc_purple_rn", "Quantity": 20}, {"Index": 5, "Type": "cwcmod:cwc_blue_rn", "Quantity": 20}], "ChatHistoryTokenized": [["<Builder>", "mission", "has", "started", "."], ["<Builder>", "rip", "me", "lol"], ["<Architect>", "now", "with", "blue", "blocks"], ["<Architect>", "beginning", "from", "the", "middle", "would", "be", "best", "to", "fit", "it", "all", "in"]], "Timestamp": "2018-04-16 20:37:44", "ScreenshotPath": "24767-Builder-chat.png", "BlocksInGrid": [], "BuilderPosition": {"X": 0.0, "Y": 3.1165013679281377, "Z": 0.0, "Yaw": -92.1, "Pitch": 65.69993}}, {"BuilderInventory": [{"Index": 0, "Type": "cwcmod:cwc_yellow_rn", "Quantity": 20}, {"Index": 1, "Type": "cwcmod:cwc_red_rn", "Quantity": 20}, {"Index": 2, "Type": "cwcmod:cwc_green_rn", "Quantity": 20}, {"Index": 3, "Type": "cwcmod:cwc_orange_rn", "Quantity": 20}, {"Index": 4, "Type": "cwcmod:cwc_purple_rn", "Quantity": 20}, {"Index": 5, "Type": "cwcmod:cwc_blue_rn", "Quantity": 19}], "ChatHistoryTokenized": [["<Builder>", "mission", "has", "started", "."], ["<Builder>", "rip", "me", "lol"], ["<Architect>", "now", "with", "blue", "blocks"], ["<Architect>", "beginning", "from", "the", "middle", "would", "be", "best", "to", "fit", "it", "all", "in"]], "Timestamp": "2018-04-16 20:37:52", "ScreenshotPath": "31912-Builder-putdown.png", "BlocksInGrid": [{"Type": "cwcmod:cwc_blue_rn", "PerspectiveCoordinates": null, "AbsoluteCoordinates": {"X": 0.0, "Y": 1.0, "Z": 0.0}}], "BuilderPosition": {"X": -0.1387075132047017, "Y": 3.506641309431348, "Z": 1.0439146656375753, "Yaw": -102.00008, "Pitch": 79.79995}}, {"BuilderInventory": [{"Index": 0, "Type": "cwcmod:cwc_yellow_rn", "Quantity": 20}, {"Index": 1, "Type": "cwcmod:cwc_red_rn", "Quantity": 20}, {"Index": 2, "Type": "cwcmod:cwc_green_rn", "Quantity": 20}, {"Index": 3, "Type": "cwcmod:cwc_orange_rn", "Quantity": 20}, {"Index": 4, "Type": "cwcmod:cwc_purple_rn", "Quantity": 20}, {"Index": 5, "Type": "cwcmod:cwc_blue_rn", "Quantity": 19}], "ChatHistoryTokenized": [["<Builder>", "mission", "has", "started", "."], ["<Builder>", "rip", "me", "lol"], ["<Architect>", "now", "with", "blue", "blocks"], ["<Architect>", "beginning", "from", "the", "middle", "would", "be", "best", "to", "fit", "it", "all", "in"], ["<Architect>", "do", "u", "have", "one", "with", "a", "darker", "shade", "of", "blue", "?"]], "Timestamp": "2018-04-16 20:38:08", "ScreenshotPath": "47761-Builder-chat.png", "BlocksInGrid": [{"Type": "cwcmod:cwc_blue_rn", "PerspectiveCoordinates": null, "AbsoluteCoordinates": {"X": 0.0, "Y": 1.0, "Z": 0.0}}], "BuilderPosition": {"X": -1.1935675811684718, "Y": 3.493425345662576, "Z": 0.5290633806259567, "Yaw": -85.65007, "Pitch": 57.89993}}, {"BuilderInventory": [{"Index": 0, "Type": "cwcmod:cwc_yellow_rn", "Quantity": 20}, {"Index": 1, "Type": "cwcmod:cwc_red_rn", "Quantity": 20}, {"Index": 2, "Type": "cwcmod:cwc_green_rn", "Quantity": 20}, {"Index": 3, "Type": "cwcmod:cwc_orange_rn", "Quantity": 20}, {"Index": 4, "Type": "cwcmod:cwc_purple_rn", "Quantity": 20}, {"Index": 5, "Type": "cwcmod:cwc_blue_rn", "Quantity": 19}], "ChatHistoryTokenized": [["<Builder>", "mission", "has", "started", "."], ["<Builder>", "rip", "me", "lol"], ["<Architect>", "now", "with", "blue", "blocks"], ["<Architect>", "beginning", "from", "the", "middle", "would", "be", "best", "to", "fit", "it", "all", "in"], ["<Architect>", "do", "u", "have", "one", "with", "a", "darker", "shade", "of", "blue", "?"], ["<Builder>", "nope", ":", "-", "("]], "Timestamp": "2018-04-16 20:38:16", "ScreenshotPath": "56509-Builder-chat.png", "BlocksInGrid": [{"Type": "cwcmod:cwc_blue_rn", "PerspectiveCoordinates": null, "AbsoluteCoordinates": {"X": 0.0, "Y": 1.0, "Z": 0.0}}], "BuilderPosition": {"X": -1.1935675811684718, "Y": 3.493425345662576, "Z": 0.5290633806259567, "Yaw": -85.65007, "Pitch": 57.89993}}, {"BuilderInventory": [{"Index": 0, "Type": "cwcmod:cwc_yellow_rn", "Quantity": 20}, {"Index": 1, "Type": "cwcmod:cwc_red_rn", "Quantity": 20}, {"Index": 2, "Type": "cwcmod:cwc_green_rn", "Quantity": 20}, {"Index": 3, "Type": "cwcmod:cwc_orange_rn", "Quantity": 20}, {"Index": 4, "Type": "cwcmod:cwc_purple_rn", "Quantity": 20}, {"Index": 5, "Type": "cwcmod:cwc_blue_rn", "Quantity": 19}], "ChatHistoryTokenized": [["<Builder>", "mission", "has", "started", "."], ["<Builder>", "rip", "me", "lol"], ["<Architect>", "now", "with", "blue", "blocks"], ["<Architect>", "beginning", "from", "the", "middle", "would", "be", "best", "to", "fit", "it", "all", "in"], ["<Architect>", "do", "u", "have", "one", "with", "a", "darker", "shade", "of", "blue", "?"], ["<Builder>", "nope", ":", "-", "("], ["<Architect>", "oh", "stop", "nvm"]], "Timestamp": "2018-04-16 20:38:20", "ScreenshotPath": "59858-Builder-chat.png", "BlocksInGrid": [{"Type": "cwcmod:cwc_blue_rn", "PerspectiveCoordinates": null, "AbsoluteCoordinates": {"X": 0.0, "Y": 1.0, "Z": 0.0}}], "BuilderPosition": {"X": -0.44456099003071314, "Y": 3.493425345662576, "Z": 0.44643624893208245, "Yaw": -82.650024, "Pitch": 84.29996}}, {"BuilderInventory": [{"Index": 0, "Type": "cwcmod:cwc_yellow_rn", "Quantity": 20}, {"Index": 1, "Type": "cwcmod:cwc_red_rn", "Quantity": 20}, {"Index": 2, "Type": "cwcmod:cwc_green_rn", "Quantity": 20}, {"Index": 3, "Type": "cwcmod:cwc_orange_rn", "Quantity": 20}, {"Index": 4, "Type": "cwcmod:cwc_purple_rn", "Quantity": 20}, {"Index": 5, "Type": "cwcmod:cwc_blue_rn", "Quantity": 19}], "ChatHistoryTokenized": [["<Builder>", "mission", "has", "started", "."], ["<Builder>", "rip", "me", "lol"], ["<Architect>", "now", "with", "blue", "blocks"], ["<Architect>", "beginning", "from", "the", "middle", "would", "be", "best", "to", "fit", "it", "all", "in"], ["<Architect>", "do", "u", "have", "one", "with", "a", "darker", "shade", "of", "blue", "?"], ["<Builder>", "nope", ":", "-", "("], ["<Architect>", "oh", "stop", "nvm"], ["<Builder>", "lmao"]], "Timestamp": "2018-04-16 20:38:23", "ScreenshotPath": "63107-Builder-chat.png", "BlocksInGrid": [{"Type": "cwcmod:cwc_blue_rn", "PerspectiveCoordinates": null, "AbsoluteCoordinates": {"X": 0.0, "Y": 1.0, "Z": 0.0}}], "BuilderPosition": {"X": -0.6123311244588255, "Y": 3.493425345662576, "Z": 0.4372983416455464, "Yaw": -91.50003, "Pitch": 71.69994}}, {"BuilderInventory": [{"Index": 0, "Type": "cwcmod:cwc_yellow_rn", "Quantity": 20}, {"Index": 1, "Type": "cwcmod:cwc_red_rn", "Quantity": 20}, {"Index": 2, "Type": "cwcmod:cwc_green_rn", "Quantity": 20}, {"Index": 3, "Type": "cwcmod:cwc_orange_rn", "Quantity": 20}, {"Index": 4, "Type": "cwcmod:cwc_purple_rn", "Quantity": 20}, {"Index": 5, "Type": "cwcmod:cwc_blue_rn", "Quantity": 19}], "ChatHistoryTokenized": [["<Builder>", "mission", "has", "started", "."], ["<Builder>", "rip", "me", "lol"], ["<Architect>", "now", "with", "blue", "blocks"], ["<Architect>", "beginning", "from", "the", "middle", "would", "be", "best", "to", "fit", "it", "all", "in"], ["<Architect>", "do", "u", "have", "one", "with", "a", "darker", "shade", "of", "blue", "?"], ["<Builder>", "nope", ":", "-", "("], ["<Architect>", "oh", "stop", "nvm"], ["<Builder>", "lmao"], ["<Architect>", "make", "a", "tower", "of", "5", "purples", "there"]], "Timestamp": "2018-04-16 20:38:35", "ScreenshotPath": "75505-Builder-chat.png", "BlocksInGrid": [{"Type": "cwcmod:cwc_blue_rn", "PerspectiveCoordinates": null, "AbsoluteCoordinates": {"X": 0.0, "Y": 1.0, "Z": 0.0}}], "BuilderPosition": {"X": -0.6218358073021673, "Y": 3.493425345662576, "Z": 0.43576002259800595, "Yaw": -87.90003, "Pitch": 72.29995}}, {"BuilderInventory": [{"Index": 0, "Type": "cwcmod:cwc_yellow_rn", "Quantity": 20}, {"Index": 1, "Type": "cwcmod:cwc_red_rn", "Quantity": 20}, {"Index": 2, "Type": "cwcmod:cwc_green_rn", "Quantity": 20}, {"Index": 3, "Type": "cwcmod:cwc_orange_rn", "Quantity": 20}, {"Index": 4, "Type": "cwcmod:cwc_purple_rn", "Quantity": 20}, {"Index": 5, "Type": "cwcmod:cwc_blue_rn", "Quantity": 18}], "ChatHistoryTokenized": [["<Builder>", "mission", "has", "started", "."], ["<Builder>", "rip", "me", "lol"], ["<Architect>", "now", "with", "blue", "blocks"], ["<Architect>", "beginning", "from", "the", "middle", "would", "be", "best", "to", "fit", "it", "all", "in"], ["<Architect>", "do", "u", "have", "one", "with", "a", "darker", "shade", "of", "blue", "?"], ["<Builder>", "nope", ":", "-", "("], ["<Architect>", "oh", "stop", "nvm"], ["<Builder>", "lmao"], ["<Architect>", "make", "a", "tower", "of", "5", "purples", "there"]], "Timestamp": "2018-04-16 20:38:39", "ScreenshotPath": "78754-Builder-putdown.png", "BlocksInGrid": [{"Type": "cwcmod:cwc_blue_rn", "PerspectiveCoordinates": null, "AbsoluteCoordinates": {"X": 0.0, "Y": 1.0, "Z": 0.0}}, {"Type": "cwcmod:cwc_blue_rn", "PerspectiveCoordinates": null, "AbsoluteCoordinates": {"X": 0.0, "Y": 2.0, "Z": 0.0}}], "BuilderPosition": {"X": -2.135831912923453, "Y": 3.493425345662576, "Z": 0.4273086159868763, "Yaw": -85.65006, "Pitch": 51.749947}}, {"BuilderInventory": [{"Index": 0, "Type": "cwcmod:cwc_yellow_rn", "Quantity": 20}, {"Index": 1, "Type": "cwcmod:cwc_red_rn", "Quantity": 20}, {"Index": 2, "Type": "cwcmod:cwc_green_rn", "Quantity": 20}, {"Index": 3, "Type": "cwcmod:cwc_orange_rn", "Quantity": 20}, {"Index": 4, "Type": "cwcmod:cwc_purple_rn", "Quantity": 20}, {"Index": 5, "Type": "cwcmod:cwc_blue_rn", "Quantity": 17}], "ChatHistoryTokenized": [["<Builder>", "mission", "has", "started", "."], ["<Builder>", "rip", "me", "lol"], ["<Architect>", "now", "with", "blue", "blocks"], ["<Architect>", "beginning", "from", "the", "middle", "would", "be", "best", "to", "fit", "it", "all", "in"], ["<Architect>", "do", "u", "have", "one", "with", "a", "darker", "shade", "of", "blue", "?"], ["<Builder>", "nope", ":", "-", "("], ["<Architect>", "oh", "stop", "nvm"], ["<Builder>", "lmao"], ["<Architect>", "make", "a", "tower", "of", "5", "purples", "there"], ["<Architect>", "including", "the", "one", "yous", "et"]], "Timestamp": "2018-04-16 20:38:40", "ScreenshotPath": "80532-Builder-putdown.png", "BlocksInGrid": [{"Type": "cwcmod:cwc_blue_rn", "PerspectiveCoordinates": null, "AbsoluteCoordinates": {"X": 0.0, "Y": 1.0, "Z": 0.0}}, {"Type": "cwcmod:cwc_blue_rn", "PerspectiveCoordinates": null, "AbsoluteCoordinates": {"X": 0.0, "Y": 2.0, "Z": 0.0}}, {"Type": "cwcmod:cwc_blue_rn", "PerspectiveCoordinates": null, "AbsoluteCoordinates": {"X": 0.0, "Y": 3.0, "Z": 0.0}}], "BuilderPosition": {"X": -2.221314700559481, "Y": 3.493425345662576, "Z": 0.4273086159868763, "Yaw": -89.40008, "Pitch": 35.99995}}, {"BuilderInventory": [{"Index": 0, "Type": "cwcmod:cwc_yellow_rn", "Quantity": 20}, {"Index": 1, "Type": "cwcmod:cwc_red_rn", "Quantity": 20}, {"Index": 2, "Type": "cwcmod:cwc_green_rn", "Quantity": 20}, {"Index": 3, "Type": "cwcmod:cwc_orange_rn", "Quantity": 20}, {"Index": 4, "Type": "cwcmod:cwc_purple_rn", "Quantity": 20}, {"Index": 5, "Type": "cwcmod:cwc_blue_rn", "Quantity": 17}], "ChatHistoryTokenized": [["<Builder>", "mission", "has", "started", "."], ["<Builder>", "rip", "me", "lol"], ["<Architect>", "now", "with", "blue", "blocks"], ["<Architect>", "beginning", "from", "the", "middle", "would", "be", "best", "to", "fit", "it", "all", "in"], ["<Architect>", "do", "u", "have", "one", "with", "a", "darker", "shade", "of", "blue", "?"], ["<Builder>", "nope", ":", "-", "("], ["<Architect>", "oh", "stop", "nvm"], ["<Builder>", "lmao"], ["<Architect>", "make", "a", "tower", "of", "5", "purples", "there"], ["<Architect>", "including", "the", "one", "yous", "et"]], "Timestamp": "2018-04-16 20:38:40", "ScreenshotPath": null, "BlocksInGrid": [{"Type": "cwcmod:cwc_blue_rn", "PerspectiveCoordinates": null, "AbsoluteCoordinates": {"X": 0.0, "Y": 1.0, "Z": 0.0}}, {"Type": "cwcmod:cwc_blue_rn", "PerspectiveCoordinates": null, "AbsoluteCoordinates": {"X": 0.0, "Y": 2.0, "Z": 0.0}}, {"Type": "cwcmod:cwc_blue_rn", "PerspectiveCoordinates": null, "AbsoluteCoordinates": {"X": 0.0, "Y": 3.0, "Z": 0.0}}], "BuilderPosition": {"X": -2.221314700559481, "Y": 3.493425345662576, "Z": 0.4273086159868763, "Yaw": -89.40008, "Pitch": 35.99995}}, {"BuilderInventory": [{"Index": 0, "Type": "cwcmod:cwc_yellow_rn", "Quantity": 20}, {"Index": 1, "Type": "cwcmod:cwc_red_rn", "Quantity": 20}, {"Index": 2, "Type": "cwcmod:cwc_green_rn", "Quantity": 20}, {"Index": 3, "Type": "cwcmod:cwc_orange_rn", "Quantity": 20}, {"Index": 4, "Type": "cwcmod:cwc_purple_rn", "Quantity": 20}, {"Index": 5, "Type": "cwcmod:cwc_blue_rn", "Quantity": 16}], "ChatHistoryTokenized": [["<Builder>", "mission", "has", "started", "."], ["<Builder>", "rip", "me", "lol"], ["<Architect>", "now", "with", "blue", "blocks"], ["<Architect>", "beginning", "from", "the", "middle", "would", "be", "best", "to", "fit", "it", "all", "in"], ["<Architect>", "do", "u", "have", "one", "with", "a", "darker", "shade", "of", "blue", "?"], ["<Builder>", "nope", ":", "-", "("], ["<Architect>", "oh", "stop", "nvm"], ["<Builder>", "lmao"], ["<Architect>", "make", "a", "tower", "of", "5", "purples", "there"], ["<Architect>", "including", "the", "one", "yous", "et"]], "Timestamp": "2018-04-16 20:38:44", "ScreenshotPath": "83704-Builder-putdown.png", "BlocksInGrid": [{"Type": "cwcmod:cwc_blue_rn", "PerspectiveCoordinates": null, "AbsoluteCoordinates": {"X": 0.0, "Y": 1.0, "Z": 0.0}}, {"Type": "cwcmod:cwc_blue_rn", "PerspectiveCoordinates": null, "AbsoluteCoordinates": {"X": 0.0, "Y": 2.0, "Z": 0.0}}, {"Type": "cwcmod:cwc_blue_rn", "PerspectiveCoordinates": null, "AbsoluteCoordinates": {"X": 0.0, "Y": 3.0, "Z": 0.0}}, {"Type": "cwcmod:cwc_blue_rn", "PerspectiveCoordinates": null, "AbsoluteCoordinates": {"X": 0.0, "Y": 4.0, "Z": 0.0}}], "BuilderPosition": {"X": -2.221314700559481, "Y": 5.363197514383684, "Z": 0.4273086159868763, "Yaw": -86.55007, "Pitch": 49.34997}}, {"BuilderInventory": [{"Index": 0, "Type": "cwcmod:cwc_yellow_rn", "Quantity": 20}, {"Index": 1, "Type": "cwcmod:cwc_red_rn", "Quantity": 20}, {"Index": 2, "Type": "cwcmod:cwc_green_rn", "Quantity": 20}, {"Index": 3, "Type": "cwcmod:cwc_orange_rn", "Quantity": 20}, {"Index": 4, "Type": "cwcmod:cwc_purple_rn", "Quantity": 20}, {"Index": 5, "Type": "cwcmod:cwc_blue_rn", "Quantity": 15}], "ChatHistoryTokenized": [["<Builder>", "mission", "has", "started", "."], ["<Builder>", "rip", "me", "lol"], ["<Architect>", "now", "with", "blue", "blocks"], ["<Architect>", "beginning", "from", "the", "middle", "would", "be", "best", "to", "fit", "it", "all", "in"], ["<Architect>", "do", "u", "have", "one", "with", "a", "darker", "shade", "of", "blue", "?"], ["<Builder>", "nope", ":", "-", "("], ["<Architect>", "oh", "stop", "nvm"], ["<Builder>", "lmao"], ["<Architect>", "make", "a", "tower", "of", "5", "purples", "there"], ["<Architect>", "including", "the", "one", "yous", "et"]], "Timestamp": "2018-04-16 20:38:45", "ScreenshotPath": "85203-Builder-putdown.png", "BlocksInGrid": [{"Type": "cwcmod:cwc_blue_rn", "PerspectiveCoordinates": null, "AbsoluteCoordinates": {"X": 0.0, "Y": 1.0, "Z": 0.0}}, {"Type": "cwcmod:cwc_blue_rn", "PerspectiveCoordinates": null, "AbsoluteCoordinates": {"X": 0.0, "Y": 2.0, "Z": 0.0}}, {"Type": "cwcmod:cwc_blue_rn", "PerspectiveCoordinates": null, "AbsoluteCoordinates": {"X": 0.0, "Y": 3.0, "Z": 0.0}}, {"Type": "cwcmod:cwc_blue_rn", "PerspectiveCoordinates": null, "AbsoluteCoordinates": {"X": 0.0, "Y": 4.0, "Z": 0.0}}, {"Type": "cwcmod:cwc_blue_rn", "PerspectiveCoordinates": null, "AbsoluteCoordinates": {"X": 0.0, "Y": 5.0, "Z": 0.0}}], "BuilderPosition": {"X": -2.221314700559481, "Y": 5.363197514383684, "Z": 0.4273086159868763, "Yaw": -88.200066, "Pitch": 38.099968}}, {"BuilderInventory": [{"Index": 0, "Type": "cwcmod:cwc_yellow_rn", "Quantity": 20}, {"Index": 1, "Type": "cwcmod:cwc_red_rn", "Quantity": 20}, {"Index": 2, "Type": "cwcmod:cwc_green_rn", "Quantity": 20}, {"Index": 3, "Type": "cwcmod:cwc_orange_rn", "Quantity": 20}, {"Index": 4, "Type": "cwcmod:cwc_purple_rn", "Quantity": 20}, {"Index": 5, "Type": "cwcmod:cwc_blue_rn", "Quantity": 15}], "ChatHistoryTokenized": [["<Builder>", "mission", "has", "started", "."], ["<Builder>", "rip", "me", "lol"], ["<Architect>", "now", "with", "blue", "blocks"], ["<Architect>", "beginning", "from", "the", "middle", "would", "be", "best", "to", "fit", "it", "all", "in"], ["<Architect>", "do", "u", "have", "one", "with", "a", "darker", "shade", "of", "blue", "?"], ["<Builder>", "nope", ":", "-", "("], ["<Architect>", "oh", "stop", "nvm"], ["<Builder>", "lmao"], ["<Architect>", "make", "a", "tower", "of", "5", "purples", "there"], ["<Architect>", "including", "the", "one", "yous", "et"], ["<Builder>", "like", "this"]], "Timestamp": "2018-04-16 20:38:58", "ScreenshotPath": "98201-Builder-chat.png", "BlocksInGrid": [{"Type": "cwcmod:cwc_blue_rn", "PerspectiveCoordinates": null, "AbsoluteCoordinates": {"X": 0.0, "Y": 1.0, "Z": 0.0}}, {"Type": "cwcmod:cwc_blue_rn", "PerspectiveCoordinates": null, "AbsoluteCoordinates": {"X": 0.0, "Y": 2.0, "Z": 0.0}}, {"Type": "cwcmod:cwc_blue_rn", "PerspectiveCoordinates": null, "AbsoluteCoordinates": {"X": 0.0, "Y": 3.0, "Z": 0.0}}, {"Type": "cwcmod:cwc_blue_rn", "PerspectiveCoordinates": null, "AbsoluteCoordinates": {"X": 0.0, "Y": 4.0, "Z": 0.0}}, {"Type": "cwcmod:cwc_blue_rn", "PerspectiveCoordinates": null, "AbsoluteCoordinates": {"X": 0.0, "Y": 5.0, "Z": 0.0}}], "BuilderPosition": {"X": -2.221314700559481, "Y": 5.363197514383684, "Z": 0.4273086159868763, "Yaw": -109.05007, "Pitch": 43.950012}}, {"BuilderInventory": [{"Index": 0, "Type": "cwcmod:cwc_yellow_rn", "Quantity": 20}, {"Index": 1, "Type": "cwcmod:cwc_red_rn", "Quantity": 20}, {"Index": 2, "Type": "cwcmod:cwc_green_rn", "Quantity": 20}, {"Index": 3, "Type": "cwcmod:cwc_orange_rn", "Quantity": 20}, {"Index": 4, "Type": "cwcmod:cwc_purple_rn", "Quantity": 20}, {"Index": 5, "Type": "cwcmod:cwc_blue_rn", "Quantity": 15}], "ChatHistoryTokenized": [["<Builder>", "mission", "has", "started", "."], ["<Builder>", "rip", "me", "lol"], ["<Architect>", "now", "with", "blue", "blocks"], ["<Architect>", "beginning", "from", "the", "middle", "would", "be", "best", "to", "fit", "it", "all", "in"], ["<Architect>", "do", "u", "have", "one", "with", "a", "darker", "shade", "of", "blue", "?"], ["<Builder>", "nope", ":", "-", "("], ["<Architect>", "oh", "stop", "nvm"], ["<Builder>", "lmao"], ["<Architect>", "make", "a", "tower", "of", "5", "purples", "there"], ["<Architect>", "including", "the", "one", "yous", "et"], ["<Builder>", "like", "this"], ["<Architect>", "yes"]], "Timestamp": "2018-04-16 20:39:01", "ScreenshotPath": "101768-Builder-chat.png", "BlocksInGrid": [{"Type": "cwcmod:cwc_blue_rn", "PerspectiveCoordinates": null, "AbsoluteCoordinates": {"X": 0.0, "Y": 1.0, "Z": 0.0}}, {"Type": "cwcmod:cwc_blue_rn", "PerspectiveCoordinates": null, "AbsoluteCoordinates": {"X": 0.0, "Y": 2.0, "Z": 0.0}}, {"Type": "cwcmod:cwc_blue_rn", "PerspectiveCoordinates": null, "AbsoluteCoordinates": {"X": 0.0, "Y": 3.0, "Z": 0.0}}, {"Type": "cwcmod:cwc_blue_rn", "PerspectiveCoordinates": null, "AbsoluteCoordinates": {"X": 0.0, "Y": 4.0, "Z": 0.0}}, {"Type": "cwcmod:cwc_blue_rn", "PerspectiveCoordinates": null, "AbsoluteCoordinates": {"X": 0.0, "Y": 5.0, "Z": 0.0}}], "BuilderPosition": {"X": -2.221314700559481, "Y": 5.363197514383684, "Z": 0.4273086159868763, "Yaw": -109.05007, "Pitch": 43.950012}}, {"BuilderInventory": [{"Index": 0, "Type": "cwcmod:cwc_yellow_rn", "Quantity": 20}, {"Index": 1, "Type": "cwcmod:cwc_red_rn", "Quantity": 20}, {"Index": 2, "Type": "cwcmod:cwc_green_rn", "Quantity": 20}, {"Index": 3, "Type": "cwcmod:cwc_orange_rn", "Quantity": 20}, {"Index": 4, "Type": "cwcmod:cwc_purple_rn", "Quantity": 20}, {"Index": 5, "Type": "cwcmod:cwc_blue_rn", "Quantity": 15}], "ChatHistoryTokenized": [["<Builder>", "mission", "has", "started", "."], ["<Builder>", "rip", "me", "lol"], ["<Architect>", "now", "with", "blue", "blocks"], ["<Architect>", "beginning", "from", "the", "middle", "would", "be", "best", "to", "fit", "it", "all", "in"], ["<Architect>", "do", "u", "have", "one", "with", "a", "darker", "shade", "of", "blue", "?"], ["<Builder>", "nope", ":", "-", "("], ["<Architect>", "oh", "stop", "nvm"], ["<Builder>", "lmao"], ["<Architect>", "make", "a", "tower", "of", "5", "purples", "there"], ["<Architect>", "including", "the", "one", "yous", "et"], ["<Builder>", "like", "this"], ["<Architect>", "yes"], ["<Builder>", "good"]], "Timestamp": "2018-04-16 20:39:05", "ScreenshotPath": "105967-Builder-chat.png", "BlocksInGrid": [{"Type": "cwcmod:cwc_blue_rn", "PerspectiveCoordinates": null, "AbsoluteCoordinates": {"X": 0.0, "Y": 1.0, "Z": 0.0}}, {"Type": "cwcmod:cwc_blue_rn", "PerspectiveCoordinates": null, "AbsoluteCoordinates": {"X": 0.0, "Y": 2.0, "Z": 0.0}}, {"Type": "cwcmod:cwc_blue_rn", "PerspectiveCoordinates": null, "AbsoluteCoordinates": {"X": 0.0, "Y": 3.0, "Z": 0.0}}, {"Type": "cwcmod:cwc_blue_rn", "PerspectiveCoordinates": null, "AbsoluteCoordinates": {"X": 0.0, "Y": 4.0, "Z": 0.0}}, {"Type": "cwcmod:cwc_blue_rn", "PerspectiveCoordinates": null, "AbsoluteCoordinates": {"X": 0.0, "Y": 5.0, "Z": 0.0}}], "BuilderPosition": {"X": -2.221314700559481, "Y": 5.363197514383684, "Z": 0.4273086159868763, "Yaw": -109.05007, "Pitch": 43.950012}}, {"BuilderInventory": [{"Index": 0, "Type": "cwcmod:cwc_yellow_rn", "Quantity": 20}, {"Index": 1, "Type": "cwcmod:cwc_red_rn", "Quantity": 20}, {"Index": 2, "Type": "cwcmod:cwc_green_rn", "Quantity": 20}, {"Index": 3, "Type": "cwcmod:cwc_orange_rn", "Quantity": 20}, {"Index": 4, "Type": "cwcmod:cwc_purple_rn", "Quantity": 20}, {"Index": 5, "Type": "cwcmod:cwc_blue_rn", "Quantity": 15}], "ChatHistoryTokenized": [["<Builder>", "mission", "has", "started", "."], ["<Builder>", "rip", "me", "lol"], ["<Architect>", "now", "with", "blue", "blocks"], ["<Architect>", "beginning", "from", "the", "middle", "would", "be", "best", "to", "fit", "it", "all", "in"], ["<Architect>", "do", "u", "have", "one", "with", "a", "darker", "shade", "of", "blue", "?"], ["<Builder>", "nope", ":", "-", "("], ["<Architect>", "oh", "stop", "nvm"], ["<Builder>", "lmao"], ["<Architect>", "make", "a", "tower", "of", "5", "purples", "there"], ["<Architect>", "including", "the", "one", "yous", "et"], ["<Builder>", "like", "this"], ["<Architect>", "yes"], ["<Builder>", "good"], ["<Architect>", "now", "on", "one", "of", "the", "4", "sides", "of", "the", "block", "(", "does", "n't", "matter", "which", ")", "put", "four", "blocks", "in", "a", "line"]], "Timestamp": "2018-04-16 20:39:29", "ScreenshotPath": "129113-Builder-chat.png", "BlocksInGrid": [{"Type": "cwcmod:cwc_blue_rn", "PerspectiveCoordinates": null, "AbsoluteCoordinates": {"X": 0.0, "Y": 1.0, "Z": 0.0}}, {"Type": "cwcmod:cwc_blue_rn", "PerspectiveCoordinates": null, "AbsoluteCoordinates": {"X": 0.0, "Y": 2.0, "Z": 0.0}}, {"Type": "cwcmod:cwc_blue_rn", "PerspectiveCoordinates": null, "AbsoluteCoordinates": {"X": 0.0, "Y": 3.0, "Z": 0.0}}, {"Type": "cwcmod:cwc_blue_rn", "PerspectiveCoordinates": null, "AbsoluteCoordinates": {"X": 0.0, "Y": 4.0, "Z": 0.0}}, {"Type": "cwcmod:cwc_blue_rn", "PerspectiveCoordinates": null, "AbsoluteCoordinates": {"X": 0.0, "Y": 5.0, "Z": 0.0}}], "BuilderPosition": {"X": -14.645990804770447, "Y": 5.363197514383684, "Z": 0.5601996148258862, "Yaw": -86.549995, "Pitch": 20.250023}}, {"BuilderInventory": [{"Index": 0, "Type": "cwcmod:cwc_yellow_rn", "Quantity": 20}, {"Index": 1, "Type": "cwcmod:cwc_red_rn", "Quantity": 20}, {"Index": 2, "Type": "cwcmod:cwc_green_rn", "Quantity": 20}, {"Index": 3, "Type": "cwcmod:cwc_orange_rn", "Quantity": 20}, {"Index": 4, "Type": "cwcmod:cwc_purple_rn", "Quantity": 20}, {"Index": 5, "Type": "cwcmod:cwc_blue_rn", "Quantity": 14}], "ChatHistoryTokenized": [["<Builder>", "mission", "has", "started", "."], ["<Builder>", "rip", "me", "lol"], ["<Architect>", "now", "with", "blue", "blocks"], ["<Architect>", "beginning", "from", "the", "middle", "would", "be", "best", "to", "fit", "it", "all", "in"], ["<Architect>", "do", "u", "have", "one", "with", "a", "darker", "shade", "of", "blue", "?"], ["<Builder>", "nope", ":", "-", "("], ["<Architect>", "oh", "stop", "nvm"], ["<Builder>", "lmao"], ["<Architect>", "make", "a", "tower", "of", "5", "purples", "there"], ["<Architect>", "including", "the", "one", "yous", "et"], ["<Builder>", "like", "this"], ["<Architect>", "yes"], ["<Builder>", "good"], ["<Architect>", "now", "on", "one", "of", "the", "4", "sides", "of", "the", "block", "(", "does", "n't", "matter", "which", ")", "put", "four", "blocks", "in", "a", "line"]], "Timestamp": "2018-04-16 20:39:37", "ScreenshotPath": "137212-Builder-putdown.png", "BlocksInGrid": [{"Type": "cwcmod:cwc_blue_rn", "PerspectiveCoordinates": null, "AbsoluteCoordinates": {"X": -1.0, "Y": 1.0, "Z": 0.0}}, {"Type": "cwcmod:cwc_blue_rn", "PerspectiveCoordinates": null, "AbsoluteCoordinates": {"X": 0.0, "Y": 1.0, "Z": 0.0}}, {"Type": "cwcmod:cwc_blue_rn", "PerspectiveCoordinates": null, "AbsoluteCoordinates": {"X": 0.0, "Y": 2.0, "Z": 0.0}}, {"Type": "cwcmod:cwc_blue_rn", "PerspectiveCoordinates": null, "AbsoluteCoordinates": {"X": 0.0, "Y": 3.0, "Z": 0.0}}, {"Type": "cwcmod:cwc_blue_rn", "PerspectiveCoordinates": null, "AbsoluteCoordinates": {"X": 0.0, "Y": 4.0, "Z": 0.0}}, {"Type": "cwcmod:cwc_blue_rn", "PerspectiveCoordinates": null, "AbsoluteCoordinates": {"X": 0.0, "Y": 5.0, "Z": 0.0}}], "BuilderPosition": {"X": -2.7604836474567556, "Y": 3.118601650137637, "Z": 0.44847134100630104, "Yaw": -89.54996, "Pitch": 57.45001}}, {"BuilderInventory": [{"Index": 0, "Type": "cwcmod:cwc_yellow_rn", "Quantity": 20}, {"Index": 1, "Type": "cwcmod:cwc_red_rn", "Quantity": 20}, {"Index": 2, "Type": "cwcmod:cwc_green_rn", "Quantity": 20}, {"Index": 3, "Type": "cwcmod:cwc_orange_rn", "Quantity": 20}, {"Index": 4, "Type": "cwcmod:cwc_purple_rn", "Quantity": 20}, {"Index": 5, "Type": "cwcmod:cwc_blue_rn", "Quantity": 13}], "ChatHistoryTokenized": [["<Builder>", "mission", "has", "started", "."], ["<Builder>", "rip", "me", "lol"], ["<Architect>", "now", "with", "blue", "blocks"], ["<Architect>", "beginning", "from", "the", "middle", "would", "be", "best", "to", "fit", "it", "all", "in"], ["<Architect>", "do", "u", "have", "one", "with", "a", "darker", "shade", "of", "blue", "?"], ["<Builder>", "nope", ":", "-", "("], ["<Architect>", "oh", "stop", "nvm"], ["<Builder>", "lmao"], ["<Architect>", "make", "a", "tower", "of", "5", "purples", "there"], ["<Architect>", "including", "the", "one", "yous", "et"], ["<Builder>", "like", "this"], ["<Architect>", "yes"], ["<Builder>", "good"], ["<Architect>", "now", "on", "one", "of", "the", "4", "sides", "of", "the", "block", "(", "does", "n't", "matter", "which", ")", "put", "four", "blocks", "in", "a", "line"]], "Timestamp": "2018-04-16 20:39:38", "ScreenshotPath": "138162-Builder-putdown.png", "BlocksInGrid": [{"Type": "cwcmod:cwc_blue_rn", "PerspectiveCoordinates": null, "AbsoluteCoordinates": {"X": -2.0, "Y": 1.0, "Z": 0.0}}, {"Type": "cwcmod:cwc_blue_rn", "PerspectiveCoordinates": null, "AbsoluteCoordinates": {"X": -1.0, "Y": 1.0, "Z": 0.0}}, {"Type": "cwcmod:cwc_blue_rn", "PerspectiveCoordinates": null, "AbsoluteCoordinates": {"X": 0.0, "Y": 1.0, "Z": 0.0}}, {"Type": "cwcmod:cwc_blue_rn", "PerspectiveCoordinates": null, "AbsoluteCoordinates": {"X": 0.0, "Y": 2.0, "Z": 0.0}}, {"Type": "cwcmod:cwc_blue_rn", "PerspectiveCoordinates": null, "AbsoluteCoordinates": {"X": 0.0, "Y": 3.0, "Z": 0.0}}, {"Type": "cwcmod:cwc_blue_rn", "PerspectiveCoordinates": null, "AbsoluteCoordinates": {"X": 0.0, "Y": 4.0, "Z": 0.0}}, {"Type": "cwcmod:cwc_blue_rn", "PerspectiveCoordinates": null, "AbsoluteCoordinates": {"X": 0.0, "Y": 5.0, "Z": 0.0}}], "BuilderPosition": {"X": -3.616407856685055, "Y": 3.118601650137637, "Z": 0.44771030238255083, "Yaw": -90.449974, "Pitch": 57.150005}}, {"BuilderInventory": [{"Index": 0, "Type": "cwcmod:cwc_yellow_rn", "Quantity": 20}, {"Index": 1, "Type": "cwcmod:cwc_red_rn", "Quantity": 20}, {"Index": 2, "Type": "cwcmod:cwc_green_rn", "Quantity": 20}, {"Index": 3, "Type": "cwcmod:cwc_orange_rn", "Quantity": 20}, {"Index": 4, "Type": "cwcmod:cwc_purple_rn", "Quantity": 20}, {"Index": 5, "Type": "cwcmod:cwc_blue_rn", "Quantity": 12}], "ChatHistoryTokenized": [["<Builder>", "mission", "has", "started", "."], ["<Builder>", "rip", "me", "lol"], ["<Architect>", "now", "with", "blue", "blocks"], ["<Architect>", "beginning", "from", "the", "middle", "would", "be", "best", "to", "fit", "it", "all", "in"], ["<Architect>", "do", "u", "have", "one", "with", "a", "darker", "shade", "of", "blue", "?"], ["<Builder>", "nope", ":", "-", "("], ["<Architect>", "oh", "stop", "nvm"], ["<Builder>", "lmao"], ["<Architect>", "make", "a", "tower", "of", "5", "purples", "there"], ["<Architect>", "including", "the", "one", "yous", "et"], ["<Builder>", "like", "this"], ["<Architect>", "yes"], ["<Builder>", "good"], ["<Architect>", "now", "on", "one", "of", "the", "4", "sides", "of", "the", "block", "(", "does", "n't", "matter", "which", ")", "put", "four", "blocks", "in", "a", "line"]], "Timestamp": "2018-04-16 20:39:39", "ScreenshotPath": "139212-Builder-putdown.png", "BlocksInGrid": [{"Type": "cwcmod:cwc_blue_rn", "PerspectiveCoordinates": null, "AbsoluteCoordinates": {"X": -3.0, "Y": 1.0, "Z": 0.0}}, {"Type": "cwcmod:cwc_blue_rn", "PerspectiveCoordinates": null, "AbsoluteCoordinates": {"X": -2.0, "Y": 1.0, "Z": 0.0}}, {"Type": "cwcmod:cwc_blue_rn", "PerspectiveCoordinates": null, "AbsoluteCoordinates": {"X": -1.0, "Y": 1.0, "Z": 0.0}}, {"Type": "cwcmod:cwc_blue_rn", "PerspectiveCoordinates": null, "AbsoluteCoordinates": {"X": 0.0, "Y": 1.0, "Z": 0.0}}, {"Type": "cwcmod:cwc_blue_rn", "PerspectiveCoordinates": null, "AbsoluteCoordinates": {"X": 0.0, "Y": 2.0, "Z": 0.0}}, {"Type": "cwcmod:cwc_blue_rn", "PerspectiveCoordinates": null, "AbsoluteCoordinates": {"X": 0.0, "Y": 3.0, "Z": 0.0}}, {"Type": "cwcmod:cwc_blue_rn", "PerspectiveCoordinates": null, "AbsoluteCoordinates": {"X": 0.0, "Y": 4.0, "Z": 0.0}}, {"Type": "cwcmod:cwc_blue_rn", "PerspectiveCoordinates": null, "AbsoluteCoordinates": {"X": 0.0, "Y": 5.0, "Z": 0.0}}], "BuilderPosition": {"X": -3.7907926991056122, "Y": 3.118601650137637, "Z": 0.44771030238255083, "Yaw": -91.79998, "Pitch": 76.500015}}, {"BuilderInventory": [{"Index": 0, "Type": "cwcmod:cwc_yellow_rn", "Quantity": 20}, {"Index": 1, "Type": "cwcmod:cwc_red_rn", "Quantity": 20}, {"Index": 2, "Type": "cwcmod:cwc_green_rn", "Quantity": 20}, {"Index": 3, "Type": "cwcmod:cwc_orange_rn", "Quantity": 20}, {"Index": 4, "Type": "cwcmod:cwc_purple_rn", "Quantity": 20}, {"Index": 5, "Type": "cwcmod:cwc_blue_rn", "Quantity": 11}], "ChatHistoryTokenized": [["<Builder>", "mission", "has", "started", "."], ["<Builder>", "rip", "me", "lol"], ["<Architect>", "now", "with", "blue", "blocks"], ["<Architect>", "beginning", "from", "the", "middle", "would", "be", "best", "to", "fit", "it", "all", "in"], ["<Architect>", "do", "u", "have", "one", "with", "a", "darker", "shade", "of", "blue", "?"], ["<Builder>", "nope", ":", "-", "("], ["<Architect>", "oh", "stop", "nvm"], ["<Builder>", "lmao"], ["<Architect>", "make", "a", "tower", "of", "5", "purples", "there"], ["<Architect>", "including", "the", "one", "yous", "et"], ["<Builder>", "like", "this"], ["<Architect>", "yes"], ["<Builder>", "good"], ["<Architect>", "now", "on", "one", "of", "the", "4", "sides", "of", "the", "block", "(", "does", "n't", "matter", "which", ")", "put", "four", "blocks", "in", "a", "line"]], "Timestamp": "2018-04-16 20:39:40", "ScreenshotPath": "139963-Builder-putdown.png", "BlocksInGrid": [{"Type": "cwcmod:cwc_blue_rn", "PerspectiveCoordinates": null, "AbsoluteCoordinates": {"X": -4.0, "Y": 1.0, "Z": 0.0}}, {"Type": "cwcmod:cwc_blue_rn", "PerspectiveCoordinates": null, "AbsoluteCoordinates": {"X": -3.0, "Y": 1.0, "Z": 0.0}}, {"Type": "cwcmod:cwc_blue_rn", "PerspectiveCoordinates": null, "AbsoluteCoordinates": {"X": -2.0, "Y": 1.0, "Z": 0.0}}, {"Type": "cwcmod:cwc_blue_rn", "PerspectiveCoordinates": null, "AbsoluteCoordinates": {"X": -1.0, "Y": 1.0, "Z": 0.0}}, {"Type": "cwcmod:cwc_blue_rn", "PerspectiveCoordinates": null, "AbsoluteCoordinates": {"X": 0.0, "Y": 1.0, "Z": 0.0}}, {"Type": "cwcmod:cwc_blue_rn", "PerspectiveCoordinates": null, "AbsoluteCoordinates": {"X": 0.0, "Y": 2.0, "Z": 0.0}}, {"Type": "cwcmod:cwc_blue_rn", "PerspectiveCoordinates": null, "AbsoluteCoordinates": {"X": 0.0, "Y": 3.0, "Z": 0.0}}, {"Type": "cwcmod:cwc_blue_rn", "PerspectiveCoordinates": null, "AbsoluteCoordinates": {"X": 0.0, "Y": 4.0, "Z": 0.0}}, {"Type": "cwcmod:cwc_blue_rn", "PerspectiveCoordinates": null, "AbsoluteCoordinates": {"X": 0.0, "Y": 5.0, "Z": 0.0}}], "BuilderPosition": {"X": -3.7907926991056122, "Y": 3.118601650137637, "Z": 0.44771030238255083, "Yaw": -87.59997, "Pitch": 84.450005}}, {"BuilderInventory": [{"Index": 0, "Type": "cwcmod:cwc_yellow_rn", "Quantity": 20}, {"Index": 1, "Type": "cwcmod:cwc_red_rn", "Quantity": 20}, {"Index": 2, "Type": "cwcmod:cwc_green_rn", "Quantity": 20}, {"Index": 3, "Type": "cwcmod:cwc_orange_rn", "Quantity": 20}, {"Index": 4, "Type": "cwcmod:cwc_purple_rn", "Quantity": 20}, {"Index": 5, "Type": "cwcmod:cwc_blue_rn", "Quantity": 11}], "ChatHistoryTokenized": [["<Builder>", "mission", "has", "started", "."], ["<Builder>", "rip", "me", "lol"], ["<Architect>", "now", "with", "blue", "blocks"], ["<Architect>", "beginning", "from", "the", "middle", "would", "be", "best", "to", "fit", "it", "all", "in"], ["<Architect>", "do", "u", "have", "one", "with", "a", "darker", "shade", "of", "blue", "?"], ["<Builder>", "nope", ":", "-", "("], ["<Architect>", "oh", "stop", "nvm"], ["<Builder>", "lmao"], ["<Architect>", "make", "a", "tower", "of", "5", "purples", "there"], ["<Architect>", "including", "the", "one", "yous", "et"], ["<Builder>", "like", "this"], ["<Architect>", "yes"], ["<Builder>", "good"], ["<Architect>", "now", "on", "one", "of", "the", "4", "sides", "of", "the", "block", "(", "does", "n't", "matter", "which", ")", "put", "four", "blocks", "in", "a", "line"], ["<Architect>", "sorry", ",", "the", "top", "brick"]], "Timestamp": "2018-04-16 20:39:45", "ScreenshotPath": "145461-Builder-chat.png", "BlocksInGrid": [{"Type": "cwcmod:cwc_blue_rn", "PerspectiveCoordinates": null, "AbsoluteCoordinates": {"X": -4.0, "Y": 1.0, "Z": 0.0}}, {"Type": "cwcmod:cwc_blue_rn", "PerspectiveCoordinates": null, "AbsoluteCoordinates": {"X": -3.0, "Y": 1.0, "Z": 0.0}}, {"Type": "cwcmod:cwc_blue_rn", "PerspectiveCoordinates": null, "AbsoluteCoordinates": {"X": -2.0, "Y": 1.0, "Z": 0.0}}, {"Type": "cwcmod:cwc_blue_rn", "PerspectiveCoordinates": null, "AbsoluteCoordinates": {"X": -1.0, "Y": 1.0, "Z": 0.0}}, {"Type": "cwcmod:cwc_blue_rn", "PerspectiveCoordinates": null, "AbsoluteCoordinates": {"X": 0.0, "Y": 1.0, "Z": 0.0}}, {"Type": "cwcmod:cwc_blue_rn", "PerspectiveCoordinates": null, "AbsoluteCoordinates": {"X": 0.0, "Y": 2.0, "Z": 0.0}}, {"Type": "cwcmod:cwc_blue_rn", "PerspectiveCoordinates": null, "AbsoluteCoordinates": {"X": 0.0, "Y": 3.0, "Z": 0.0}}, {"Type": "cwcmod:cwc_blue_rn", "PerspectiveCoordinates": null, "AbsoluteCoordinates": {"X": 0.0, "Y": 4.0, "Z": 0.0}}, {"Type": "cwcmod:cwc_blue_rn", "PerspectiveCoordinates": null, "AbsoluteCoordinates": {"X": 0.0, "Y": 5.0, "Z": 0.0}}], "BuilderPosition": {"X": -0.039148764129763286, "Y": 6.862967371410732, "Z": -6.110944261959782, "Yaw": 8.700051, "Pitch": 37.650013}}, {"BuilderInventory": [{"Index": 0, "Type": "cwcmod:cwc_yellow_rn", "Quantity": 20}, {"Index": 1, "Type": "cwcmod:cwc_red_rn", "Quantity": 20}, {"Index": 2, "Type": "cwcmod:cwc_green_rn", "Quantity": 20}, {"Index": 3, "Type": "cwcmod:cwc_orange_rn", "Quantity": 20}, {"Index": 4, "Type": "cwcmod:cwc_purple_rn", "Quantity": 20}, {"Index": 5, "Type": "cwcmod:cwc_blue_rn", "Quantity": 12}], "ChatHistoryTokenized": [["<Builder>", "mission", "has", "started", "."], ["<Builder>", "rip", "me", "lol"], ["<Architect>", "now", "with", "blue", "blocks"], ["<Architect>", "beginning", "from", "the", "middle", "would", "be", "best", "to", "fit", "it", "all", "in"], ["<Architect>", "do", "u", "have", "one", "with", "a", "darker", "shade", "of", "blue", "?"], ["<Builder>", "nope", ":", "-", "("], ["<Architect>", "oh", "stop", "nvm"], ["<Builder>", "lmao"], ["<Architect>", "make", "a", "tower", "of", "5", "purples", "there"], ["<Architect>", "including", "the", "one", "yous", "et"], ["<Builder>", "like", "this"], ["<Architect>", "yes"], ["<Builder>", "good"], ["<Architect>", "now", "on", "one", "of", "the", "4", "sides", "of", "the", "block", "(", "does", "n't", "matter", "which", ")", "put", "four", "blocks", "in", "a", "line"], ["<Architect>", "sorry", ",", "the", "top", "brick"]], "Timestamp": "2018-04-16 20:39:59", "ScreenshotPath": "159961-Builder-pickup.png", "BlocksInGrid": [{"Type": "cwcmod:cwc_blue_rn", "PerspectiveCoordinates": null, "AbsoluteCoordinates": {"X": -3.0, "Y": 1.0, "Z": 0.0}}, {"Type": "cwcmod:cwc_blue_rn", "PerspectiveCoordinates": null, "AbsoluteCoordinates": {"X": -2.0, "Y": 1.0, "Z": 0.0}}, {"Type": "cwcmod:cwc_blue_rn", "PerspectiveCoordinates": null, "AbsoluteCoordinates": {"X": -1.0, "Y": 1.0, "Z": 0.0}}, {"Type": "cwcmod:cwc_blue_rn", "PerspectiveCoordinates": null, "AbsoluteCoordinates": {"X": 0.0, "Y": 1.0, "Z": 0.0}}, {"Type": "cwcmod:cwc_blue_rn", "PerspectiveCoordinates": null, "AbsoluteCoordinates": {"X": 0.0, "Y": 2.0, "Z": 0.0}}, {"Type": "cwcmod:cwc_blue_rn", "PerspectiveCoordinates": null, "AbsoluteCoordinates": {"X": 0.0, "Y": 3.0, "Z": 0.0}}, {"Type": "cwcmod:cwc_blue_rn", "PerspectiveCoordinates": null, "AbsoluteCoordinates": {"X": 0.0, "Y": 4.0, "Z": 0.0}}, {"Type": "cwcmod:cwc_blue_rn", "PerspectiveCoordinates": null, "AbsoluteCoordinates": {"X": 0.0, "Y": 5.0, "Z": 0.0}}], "BuilderPosition": {"X": -4.389501849010965, "Y": 2.776440493122749, "Z": 0.7904087265998201, "Yaw": -99.89993, "Pitch": 66.90003}}, {"BuilderInventory": [{"Index": 0, "Type": "cwcmod:cwc_yellow_rn", "Quantity": 20}, {"Index": 1, "Type": "cwcmod:cwc_red_rn", "Quantity": 20}, {"Index": 2, "Type": "cwcmod:cwc_green_rn", "Quantity": 20}, {"Index": 3, "Type": "cwcmod:cwc_orange_rn", "Quantity": 20}, {"Index": 4, "Type": "cwcmod:cwc_purple_rn", "Quantity": 20}, {"Index": 5, "Type": "cwcmod:cwc_blue_rn", "Quantity": 13}], "ChatHistoryTokenized": [["<Builder>", "mission", "has", "started", "."], ["<Builder>", "rip", "me", "lol"], ["<Architect>", "now", "with", "blue", "blocks"], ["<Architect>", "beginning", "from", "the", "middle", "would", "be", "best", "to", "fit", "it", "all", "in"], ["<Architect>", "do", "u", "have", "one", "with", "a", "darker", "shade", "of", "blue", "?"], ["<Builder>", "nope", ":", "-", "("], ["<Architect>", "oh", "stop", "nvm"], ["<Builder>", "lmao"], ["<Architect>", "make", "a", "tower", "of", "5", "purples", "there"], ["<Architect>", "including", "the", "one", "yous", "et"], ["<Builder>", "like", "this"], ["<Architect>", "yes"], ["<Builder>", "good"], ["<Architect>", "now", "on", "one", "of", "the", "4", "sides", "of", "the", "block", "(", "does", "n't", "matter", "which", ")", "put", "four", "blocks", "in", "a", "line"], ["<Architect>", "sorry", ",", "the", "top", "brick"]], "Timestamp": "2018-04-16 20:40:00", "ScreenshotPath": "160411-Builder-pickup.png", "BlocksInGrid": [{"Type": "cwcmod:cwc_blue_rn", "PerspectiveCoordinates": null, "AbsoluteCoordinates": {"X": -2.0, "Y": 1.0, "Z": 0.0}}, {"Type": "cwcmod:cwc_blue_rn", "PerspectiveCoordinates": null, "AbsoluteCoordinates": {"X": -1.0, "Y": 1.0, "Z": 0.0}}, {"Type": "cwcmod:cwc_blue_rn", "PerspectiveCoordinates": null, "AbsoluteCoordinates": {"X": 0.0, "Y": 1.0, "Z": 0.0}}, {"Type": "cwcmod:cwc_blue_rn", "PerspectiveCoordinates": null, "AbsoluteCoordinates": {"X": 0.0, "Y": 2.0, "Z": 0.0}}, {"Type": "cwcmod:cwc_blue_rn", "PerspectiveCoordinates": null, "AbsoluteCoordinates": {"X": 0.0, "Y": 3.0, "Z": 0.0}}, {"Type": "cwcmod:cwc_blue_rn", "PerspectiveCoordinates": null, "AbsoluteCoordinates": {"X": 0.0, "Y": 4.0, "Z": 0.0}}, {"Type": "cwcmod:cwc_blue_rn", "PerspectiveCoordinates": null, "AbsoluteCoordinates": {"X": 0.0, "Y": 5.0, "Z": 0.0}}], "BuilderPosition": {"X": -4.389501849010965, "Y": 2.776440493122749, "Z": 0.7904087265998201, "Yaw": -96.74993, "Pitch": 50.700027}}, {"BuilderInventory": [{"Index": 0, "Type": "cwcmod:cwc_yellow_rn", "Quantity": 20}, {"Index": 1, "Type": "cwcmod:cwc_red_rn", "Quantity": 20}, {"Index": 2, "Type": "cwcmod:cwc_green_rn", "Quantity": 20}, {"Index": 3, "Type": "cwcmod:cwc_orange_rn", "Quantity": 20}, {"Index": 4, "Type": "cwcmod:cwc_purple_rn", "Quantity": 20}, {"Index": 5, "Type": "cwcmod:cwc_blue_rn", "Quantity": 14}], "ChatHistoryTokenized": [["<Builder>", "mission", "has", "started", "."], ["<Builder>", "rip", "me", "lol"], ["<Architect>", "now", "with", "blue", "blocks"], ["<Architect>", "beginning", "from", "the", "middle", "would", "be", "best", "to", "fit", "it", "all", "in"], ["<Architect>", "do", "u", "have", "one", "with", "a", "darker", "shade", "of", "blue", "?"], ["<Builder>", "nope", ":", "-", "("], ["<Architect>", "oh", "stop", "nvm"], ["<Builder>", "lmao"], ["<Architect>", "make", "a", "tower", "of", "5", "purples", "there"], ["<Architect>", "including", "the", "one", "yous", "et"], ["<Builder>", "like", "this"], ["<Architect>", "yes"], ["<Builder>", "good"], ["<Architect>", "now", "on", "one", "of", "the", "4", "sides", "of", "the", "block", "(", "does", "n't", "matter", "which", ")", "put", "four", "blocks", "in", "a", "line"], ["<Architect>", "sorry", ",", "the", "top", "brick"]], "Timestamp": "2018-04-16 20:40:00", "ScreenshotPath": "160959-Builder-pickup.png", "BlocksInGrid": [{"Type": "cwcmod:cwc_blue_rn", "PerspectiveCoordinates": null, "AbsoluteCoordinates": {"X": -2.0, "Y": 1.0, "Z": 0.0}}, {"Type": "cwcmod:cwc_blue_rn", "PerspectiveCoordinates": null, "AbsoluteCoordinates": {"X": 0.0, "Y": 1.0, "Z": 0.0}}, {"Type": "cwcmod:cwc_blue_rn", "PerspectiveCoordinates": null, "AbsoluteCoordinates": {"X": 0.0, "Y": 2.0, "Z": 0.0}}, {"Type": "cwcmod:cwc_blue_rn", "PerspectiveCoordinates": null, "AbsoluteCoordinates": {"X": 0.0, "Y": 3.0, "Z": 0.0}}, {"Type": "cwcmod:cwc_blue_rn", "PerspectiveCoordinates": null, "AbsoluteCoordinates": {"X": 0.0, "Y": 4.0, "Z": 0.0}}, {"Type": "cwcmod:cwc_blue_rn", "PerspectiveCoordinates": null, "AbsoluteCoordinates": {"X": 0.0, "Y": 5.0, "Z": 0.0}}], "BuilderPosition": {"X": -4.389501849010965, "Y": 2.7568251573534814, "Z": 0.7904087265998201, "Yaw": -94.19993, "Pitch": 34.050026}}, {"BuilderInventory": [{"Index": 0, "Type": "cwcmod:cwc_yellow_rn", "Quantity": 20}, {"Index": 1, "Type": "cwcmod:cwc_red_rn", "Quantity": 20}, {"Index": 2, "Type": "cwcmod:cwc_green_rn", "Quantity": 20}, {"Index": 3, "Type": "cwcmod:cwc_orange_rn", "Quantity": 20}, {"Index": 4, "Type": "cwcmod:cwc_purple_rn", "Quantity": 20}, {"Index": 5, "Type": "cwcmod:cwc_blue_rn", "Quantity": 15}], "ChatHistoryTokenized": [["<Builder>", "mission", "has", "started", "."], ["<Builder>", "rip", "me", "lol"], ["<Architect>", "now", "with", "blue", "blocks"], ["<Architect>", "beginning", "from", "the", "middle", "would", "be", "best", "to", "fit", "it", "all", "in"], ["<Architect>", "do", "u", "have", "one", "with", "a", "darker", "shade", "of", "blue", "?"], ["<Builder>", "nope", ":", "-", "("], ["<Architect>", "oh", "stop", "nvm"], ["<Builder>", "lmao"], ["<Architect>", "make", "a", "tower", "of", "5", "purples", "there"], ["<Architect>", "including", "the", "one", "yous", "et"], ["<Builder>", "like", "this"], ["<Architect>", "yes"], ["<Builder>", "good"], ["<Architect>", "now", "on", "one", "of", "the", "4", "sides", "of", "the", "block", "(", "does", "n't", "matter", "which", ")", "put", "four", "blocks", "in", "a", "line"], ["<Architect>", "sorry", ",", "the", "top", "brick"]], "Timestamp": "2018-04-16 20:40:01", "ScreenshotPath": "161512-Builder-pickup.png", "BlocksInGrid": [{"Type": "cwcmod:cwc_blue_rn", "PerspectiveCoordinates": null, "AbsoluteCoordinates": {"X": 0.0, "Y": 1.0, "Z": 0.0}}, {"Type": "cwcmod:cwc_blue_rn", "PerspectiveCoordinates": null, "AbsoluteCoordinates": {"X": 0.0, "Y": 2.0, "Z": 0.0}}, {"Type": "cwcmod:cwc_blue_rn", "PerspectiveCoordinates": null, "AbsoluteCoordinates": {"X": 0.0, "Y": 3.0, "Z": 0.0}}, {"Type": "cwcmod:cwc_blue_rn", "PerspectiveCoordinates": null, "AbsoluteCoordinates": {"X": 0.0, "Y": 4.0, "Z": 0.0}}, {"Type": "cwcmod:cwc_blue_rn", "PerspectiveCoordinates": null, "AbsoluteCoordinates": {"X": 0.0, "Y": 5.0, "Z": 0.0}}], "BuilderPosition": {"X": -4.389501849010965, "Y": 2.7568251573534814, "Z": 0.7904087265998201, "Yaw": -93.74992, "Pitch": 43.650024}}, {"BuilderInventory": [{"Index": 0, "Type": "cwcmod:cwc_yellow_rn", "Quantity": 20}, {"Index": 1, "Type": "cwcmod:cwc_red_rn", "Quantity": 20}, {"Index": 2, "Type": "cwcmod:cwc_green_rn", "Quantity": 20}, {"Index": 3, "Type": "cwcmod:cwc_orange_rn", "Quantity": 20}, {"Index": 4, "Type": "cwcmod:cwc_purple_rn", "Quantity": 20}, {"Index": 5, "Type": "cwcmod:cwc_blue_rn", "Quantity": 14}], "ChatHistoryTokenized": [["<Builder>", "mission", "has", "started", "."], ["<Builder>", "rip", "me", "lol"], ["<Architect>", "now", "with", "blue", "blocks"], ["<Architect>", "beginning", "from", "the", "middle", "would", "be", "best", "to", "fit", "it", "all", "in"], ["<Architect>", "do", "u", "have", "one", "with", "a", "darker", "shade", "of", "blue", "?"], ["<Builder>", "nope", ":", "-", "("], ["<Architect>", "oh", "stop", "nvm"], ["<Builder>", "lmao"], ["<Architect>", "make", "a", "tower", "of", "5", "purples", "there"], ["<Architect>", "including", "the", "one", "yous", "et"], ["<Builder>", "like", "this"], ["<Architect>", "yes"], ["<Builder>", "good"], ["<Architect>", "now", "on", "one", "of", "the", "4", "sides", "of", "the", "block", "(", "does", "n't", "matter", "which", ")", "put", "four", "blocks", "in", "a", "line"], ["<Architect>", "sorry", ",", "the", "top", "brick"]], "Timestamp": "2018-04-16 20:40:05", "ScreenshotPath": "165658-Builder-putdown.png", "BlocksInGrid": [{"Type": "cwcmod:cwc_blue_rn", "PerspectiveCoordinates": null, "AbsoluteCoordinates": {"X": 0.0, "Y": 1.0, "Z": 0.0}}, {"Type": "cwcmod:cwc_blue_rn", "PerspectiveCoordinates": null, "AbsoluteCoordinates": {"X": 0.0, "Y": 2.0, "Z": 0.0}}, {"Type": "cwcmod:cwc_blue_rn", "PerspectiveCoordinates": null, "AbsoluteCoordinates": {"X": 0.0, "Y": 3.0, "Z": 0.0}}, {"Type": "cwcmod:cwc_blue_rn", "PerspectiveCoordinates": null, "AbsoluteCoordinates": {"X": 0.0, "Y": 4.0, "Z": 0.0}}, {"Type": "cwcmod:cwc_blue_rn", "PerspectiveCoordinates": null, "AbsoluteCoordinates": {"X": -1.0, "Y": 5.0, "Z": 0.0}}, {"Type": "cwcmod:cwc_blue_rn", "PerspectiveCoordinates": null, "AbsoluteCoordinates": {"X": 0.0, "Y": 5.0, "Z": 0.0}}], "BuilderPosition": {"X": -2.8150418622501223, "Y": 3.49422806665524, "Z": 0.7059799874360979, "Yaw": -93.14992, "Pitch": -4.949978}}, {"BuilderInventory": [{"Index": 0, "Type": "cwcmod:cwc_yellow_rn", "Quantity": 20}, {"Index": 1, "Type": "cwcmod:cwc_red_rn", "Quantity": 20}, {"Index": 2, "Type": "cwcmod:cwc_green_rn", "Quantity": 20}, {"Index": 3, "Type": "cwcmod:cwc_orange_rn", "Quantity": 20}, {"Index": 4, "Type": "cwcmod:cwc_purple_rn", "Quantity": 20}, {"Index": 5, "Type": "cwcmod:cwc_blue_rn", "Quantity": 13}], "ChatHistoryTokenized": [["<Builder>", "mission", "has", "started", "."], ["<Builder>", "rip", "me", "lol"], ["<Architect>", "now", "with", "blue", "blocks"], ["<Architect>", "beginning", "from", "the", "middle", "would", "be", "best", "to", "fit", "it", "all", "in"], ["<Architect>", "do", "u", "have", "one", "with", "a", "darker", "shade", "of", "blue", "?"], ["<Builder>", "nope", ":", "-", "("], ["<Architect>", "oh", "stop", "nvm"], ["<Builder>", "lmao"], ["<Architect>", "make", "a", "tower", "of", "5", "purples", "there"], ["<Architect>", "including", "the", "one", "yous", "et"], ["<Builder>", "like", "this"], ["<Architect>", "yes"], ["<Builder>", "good"], ["<Architect>", "now", "on", "one", "of", "the", "4", "sides", "of", "the", "block", "(", "does", "n't", "matter", "which", ")", "put", "four", "blocks", "in", "a", "line"], ["<Architect>", "sorry", ",", "the", "top", "brick"]], "Timestamp": "2018-04-16 20:40:07", "ScreenshotPath": "167558-Builder-putdown.png", "BlocksInGrid": [{"Type": "cwcmod:cwc_blue_rn", "PerspectiveCoordinates": null, "AbsoluteCoordinates": {"X": 0.0, "Y": 1.0, "Z": 0.0}}, {"Type": "cwcmod:cwc_blue_rn", "PerspectiveCoordinates": null, "AbsoluteCoordinates": {"X": 0.0, "Y": 2.0, "Z": 0.0}}, {"Type": "cwcmod:cwc_blue_rn", "PerspectiveCoordinates": null, "AbsoluteCoordinates": {"X": 0.0, "Y": 3.0, "Z": 0.0}}, {"Type": "cwcmod:cwc_blue_rn", "PerspectiveCoordinates": null, "AbsoluteCoordinates": {"X": 0.0, "Y": 4.0, "Z": 0.0}}, {"Type": "cwcmod:cwc_blue_rn", "PerspectiveCoordinates": null, "AbsoluteCoordinates": {"X": -2.0, "Y": 5.0, "Z": 0.0}}, {"Type": "cwcmod:cwc_blue_rn", "PerspectiveCoordinates": null, "AbsoluteCoordinates": {"X": -1.0, "Y": 5.0, "Z": 0.0}}, {"Type": "cwcmod:cwc_blue_rn", "PerspectiveCoordinates": null, "AbsoluteCoordinates": {"X": 0.0, "Y": 5.0, "Z": 0.0}}], "BuilderPosition": {"X": -2.403254627577104, "Y": 3.49422806665524, "Z": 3.021292712942807, "Yaw": -145.19989, "Pitch": -7.9499803}}, {"BuilderInventory": [{"Index": 0, "Type": "cwcmod:cwc_yellow_rn", "Quantity": 20}, {"Index": 1, "Type": "cwcmod:cwc_red_rn", "Quantity": 20}, {"Index": 2, "Type": "cwcmod:cwc_green_rn", "Quantity": 20}, {"Index": 3, "Type": "cwcmod:cwc_orange_rn", "Quantity": 20}, {"Index": 4, "Type": "cwcmod:cwc_purple_rn", "Quantity": 20}, {"Index": 5, "Type": "cwcmod:cwc_blue_rn", "Quantity": 12}], "ChatHistoryTokenized": [["<Builder>", "mission", "has", "started", "."], ["<Builder>", "rip", "me", "lol"], ["<Architect>", "now", "with", "blue", "blocks"], ["<Architect>", "beginning", "from", "the", "middle", "would", "be", "best", "to", "fit", "it", "all", "in"], ["<Architect>", "do", "u", "have", "one", "with", "a", "darker", "shade", "of", "blue", "?"], ["<Builder>", "nope", ":", "-", "("], ["<Architect>", "oh", "stop", "nvm"], ["<Builder>", "lmao"], ["<Architect>", "make", "a", "tower", "of", "5", "purples", "there"], ["<Architect>", "including", "the", "one", "yous", "et"], ["<Builder>", "like", "this"], ["<Architect>", "yes"], ["<Builder>", "good"], ["<Architect>", "now", "on", "one", "of", "the", "4", "sides", "of", "the", "block", "(", "does", "n't", "matter", "which", ")", "put", "four", "blocks", "in", "a", "line"], ["<Architect>", "sorry", ",", "the", "top", "brick"]], "Timestamp": "2018-04-16 20:40:09", "ScreenshotPath": "169257-Builder-putdown.png", "BlocksInGrid": [{"Type": "cwcmod:cwc_blue_rn", "PerspectiveCoordinates": null, "AbsoluteCoordinates": {"X": 0.0, "Y": 1.0, "Z": 0.0}}, {"Type": "cwcmod:cwc_blue_rn", "PerspectiveCoordinates": null, "AbsoluteCoordinates": {"X": 0.0, "Y": 2.0, "Z": 0.0}}, {"Type": "cwcmod:cwc_blue_rn", "PerspectiveCoordinates": null, "AbsoluteCoordinates": {"X": 0.0, "Y": 3.0, "Z": 0.0}}, {"Type": "cwcmod:cwc_blue_rn", "PerspectiveCoordinates": null, "AbsoluteCoordinates": {"X": 0.0, "Y": 4.0, "Z": 0.0}}, {"Type": "cwcmod:cwc_blue_rn", "PerspectiveCoordinates": null, "AbsoluteCoordinates": {"X": -3.0, "Y": 5.0, "Z": 0.0}}, {"Type": "cwcmod:cwc_blue_rn", "PerspectiveCoordinates": null, "AbsoluteCoordinates": {"X": -2.0, "Y": 5.0, "Z": 0.0}}, {"Type": "cwcmod:cwc_blue_rn", "PerspectiveCoordinates": null, "AbsoluteCoordinates": {"X": -1.0, "Y": 5.0, "Z": 0.0}}, {"Type": "cwcmod:cwc_blue_rn", "PerspectiveCoordinates": null, "AbsoluteCoordinates": {"X": 0.0, "Y": 5.0, "Z": 0.0}}], "BuilderPosition": {"X": -2.3725763055246563, "Y": 3.49422806665524, "Z": 3.320948427607886, "Yaw": -172.34995, "Pitch": -3.1499803}}, {"BuilderInventory": [{"Index": 0, "Type": "cwcmod:cwc_yellow_rn", "Quantity": 20}, {"Index": 1, "Type": "cwcmod:cwc_red_rn", "Quantity": 20}, {"Index": 2, "Type": "cwcmod:cwc_green_rn", "Quantity": 20}, {"Index": 3, "Type": "cwcmod:cwc_orange_rn", "Quantity": 20}, {"Index": 4, "Type": "cwcmod:cwc_purple_rn", "Quantity": 20}, {"Index": 5, "Type": "cwcmod:cwc_blue_rn", "Quantity": 12}], "ChatHistoryTokenized": [["<Builder>", "mission", "has", "started", "."], ["<Builder>", "rip", "me", "lol"], ["<Architect>", "now", "with", "blue", "blocks"], ["<Architect>", "beginning", "from", "the", "middle", "would", "be", "best", "to", "fit", "it", "all", "in"], ["<Architect>", "do", "u", "have", "one", "with", "a", "darker", "shade", "of", "blue", "?"], ["<Builder>", "nope", ":", "-", "("], ["<Architect>", "oh", "stop", "nvm"], ["<Builder>", "lmao"], ["<Architect>", "make", "a", "tower", "of", "5", "purples", "there"], ["<Architect>", "including", "the", "one", "yous", "et"], ["<Builder>", "like", "this"], ["<Architect>", "yes"], ["<Builder>", "good"], ["<Architect>", "now", "on", "one", "of", "the", "4", "sides", "of", "the", "block", "(", "does", "n't", "matter", "which", ")", "put", "four", "blocks", "in", "a", "line"], ["<Architect>", "sorry", ",", "the", "top", "brick"], ["<Architect>", "one", "more", "and", "it", "'ll", "be", "right"]], "Timestamp": "2018-04-16 20:40:19", "ScreenshotPath": "178807-Builder-chat.png", "BlocksInGrid": [{"Type": "cwcmod:cwc_blue_rn", "PerspectiveCoordinates": null, "AbsoluteCoordinates": {"X": 0.0, "Y": 1.0, "Z": 0.0}}, {"Type": "cwcmod:cwc_blue_rn", "PerspectiveCoordinates": null, "AbsoluteCoordinates": {"X": 0.0, "Y": 2.0, "Z": 0.0}}, {"Type": "cwcmod:cwc_blue_rn", "PerspectiveCoordinates": null, "AbsoluteCoordinates": {"X": 0.0, "Y": 3.0, "Z": 0.0}}, {"Type": "cwcmod:cwc_blue_rn", "PerspectiveCoordinates": null, "AbsoluteCoordinates": {"X": 0.0, "Y": 4.0, "Z": 0.0}}, {"Type": "cwcmod:cwc_blue_rn", "PerspectiveCoordinates": null, "AbsoluteCoordinates": {"X": -3.0, "Y": 5.0, "Z": 0.0}}, {"Type": "cwcmod:cwc_blue_rn", "PerspectiveCoordinates": null, "AbsoluteCoordinates": {"X": -2.0, "Y": 5.0, "Z": 0.0}}, {"Type": "cwcmod:cwc_blue_rn", "PerspectiveCoordinates": null, "AbsoluteCoordinates": {"X": -1.0, "Y": 5.0, "Z": 0.0}}, {"Type": "cwcmod:cwc_blue_rn", "PerspectiveCoordinates": null, "AbsoluteCoordinates": {"X": 0.0, "Y": 5.0, "Z": 0.0}}], "BuilderPosition": {"X": -1.6286368952561214, "Y": 3.49422806665524, "Z": 8.640790980724326, "Yaw": -173.99988, "Pitch": 16.650015}}, {"BuilderInventory": [{"Index": 0, "Type": "cwcmod:cwc_yellow_rn", "Quantity": 20}, {"Index": 1, "Type": "cwcmod:cwc_red_rn", "Quantity": 20}, {"Index": 2, "Type": "cwcmod:cwc_green_rn", "Quantity": 20}, {"Index": 3, "Type": "cwcmod:cwc_orange_rn", "Quantity": 20}, {"Index": 4, "Type": "cwcmod:cwc_purple_rn", "Quantity": 20}, {"Index": 5, "Type": "cwcmod:cwc_blue_rn", "Quantity": 11}], "ChatHistoryTokenized": [["<Builder>", "mission", "has", "started", "."], ["<Builder>", "rip", "me", "lol"], ["<Architect>", "now", "with", "blue", "blocks"], ["<Architect>", "beginning", "from", "the", "middle", "would", "be", "best", "to", "fit", "it", "all", "in"], ["<Architect>", "do", "u", "have", "one", "with", "a", "darker", "shade", "of", "blue", "?"], ["<Builder>", "nope", ":", "-", "("], ["<Architect>", "oh", "stop", "nvm"], ["<Builder>", "lmao"], ["<Architect>", "make", "a", "tower", "of", "5", "purples", "there"], ["<Architect>", "including", "the", "one", "yous", "et"], ["<Builder>", "like", "this"], ["<Architect>", "yes"], ["<Builder>", "good"], ["<Architect>", "now", "on", "one", "of", "the", "4", "sides", "of", "the", "block", "(", "does", "n't", "matter", "which", ")", "put", "four", "blocks", "in", "a", "line"], ["<Architect>", "sorry", ",", "the", "top", "brick"], ["<Architect>", "one", "more", "and", "it", "'ll", "be", "right"]], "Timestamp": "2018-04-16 20:40:22", "ScreenshotPath": "182306-Builder-putdown.png", "BlocksInGrid": [{"Type": "cwcmod:cwc_blue_rn", "PerspectiveCoordinates": null, "AbsoluteCoordinates": {"X": 0.0, "Y": 1.0, "Z": 0.0}}, {"Type": "cwcmod:cwc_blue_rn", "PerspectiveCoordinates": null, "AbsoluteCoordinates": {"X": 0.0, "Y": 2.0, "Z": 0.0}}, {"Type": "cwcmod:cwc_blue_rn", "PerspectiveCoordinates": null, "AbsoluteCoordinates": {"X": 0.0, "Y": 3.0, "Z": 0.0}}, {"Type": "cwcmod:cwc_blue_rn", "PerspectiveCoordinates": null, "AbsoluteCoordinates": {"X": 0.0, "Y": 4.0, "Z": 0.0}}, {"Type": "cwcmod:cwc_blue_rn", "PerspectiveCoordinates": null, "AbsoluteCoordinates": {"X": -4.0, "Y": 5.0, "Z": 0.0}}, {"Type": "cwcmod:cwc_blue_rn", "PerspectiveCoordinates": null, "AbsoluteCoordinates": {"X": -3.0, "Y": 5.0, "Z": 0.0}}, {"Type": "cwcmod:cwc_blue_rn", "PerspectiveCoordinates": null, "AbsoluteCoordinates": {"X": -2.0, "Y": 5.0, "Z": 0.0}}, {"Type": "cwcmod:cwc_blue_rn", "PerspectiveCoordinates": null, "AbsoluteCoordinates": {"X": -1.0, "Y": 5.0, "Z": 0.0}}, {"Type": "cwcmod:cwc_blue_rn", "PerspectiveCoordinates": null, "AbsoluteCoordinates": {"X": 0.0, "Y": 5.0, "Z": 0.0}}], "BuilderPosition": {"X": -7.016419683145282, "Y": 3.49422806665524, "Z": -0.603775383773967, "Yaw": -77.54986, "Pitch": -4.9499855}}, {"BuilderInventory": [{"Index": 0, "Type": "cwcmod:cwc_yellow_rn", "Quantity": 20}, {"Index": 1, "Type": "cwcmod:cwc_red_rn", "Quantity": 20}, {"Index": 2, "Type": "cwcmod:cwc_green_rn", "Quantity": 20}, {"Index": 3, "Type": "cwcmod:cwc_orange_rn", "Quantity": 20}, {"Index": 4, "Type": "cwcmod:cwc_purple_rn", "Quantity": 20}, {"Index": 5, "Type": "cwcmod:cwc_blue_rn", "Quantity": 11}], "ChatHistoryTokenized": [["<Builder>", "mission", "has", "started", "."], ["<Builder>", "rip", "me", "lol"], ["<Architect>", "now", "with", "blue", "blocks"], ["<Architect>", "beginning", "from", "the", "middle", "would", "be", "best", "to", "fit", "it", "all", "in"], ["<Architect>", "do", "u", "have", "one", "with", "a", "darker", "shade", "of", "blue", "?"], ["<Builder>", "nope", ":", "-", "("], ["<Architect>", "oh", "stop", "nvm"], ["<Builder>", "lmao"], ["<Architect>", "make", "a", "tower", "of", "5", "purples", "there"], ["<Architect>", "including", "the", "one", "yous", "et"], ["<Builder>", "like", "this"], ["<Architect>", "yes"], ["<Builder>", "good"], ["<Architect>", "now", "on", "one", "of", "the", "4", "sides", "of", "the", "block", "(", "does", "n't", "matter", "which", ")", "put", "four", "blocks", "in", "a", "line"], ["<Architect>", "sorry", ",", "the", "top", "brick"], ["<Architect>", "one", "more", "and", "it", "'ll", "be", "right"], ["<Architect>", "okay", ",", "now", "add", "one", "above", "and", "under", "to", "the", "second", "from", "last", "brick"]], "Timestamp": "2018-04-16 20:40:41", "ScreenshotPath": "201219-Builder-chat.png", "BlocksInGrid": [{"Type": "cwcmod:cwc_blue_rn", "PerspectiveCoordinates": null, "AbsoluteCoordinates": {"X": 0.0, "Y": 1.0, "Z": 0.0}}, {"Type": "cwcmod:cwc_blue_rn", "PerspectiveCoordinates": null, "AbsoluteCoordinates": {"X": 0.0, "Y": 2.0, "Z": 0.0}}, {"Type": "cwcmod:cwc_blue_rn", "PerspectiveCoordinates": null, "AbsoluteCoordinates": {"X": 0.0, "Y": 3.0, "Z": 0.0}}, {"Type": "cwcmod:cwc_blue_rn", "PerspectiveCoordinates": null, "AbsoluteCoordinates": {"X": 0.0, "Y": 4.0, "Z": 0.0}}, {"Type": "cwcmod:cwc_blue_rn", "PerspectiveCoordinates": null, "AbsoluteCoordinates": {"X": -4.0, "Y": 5.0, "Z": 0.0}}, {"Type": "cwcmod:cwc_blue_rn", "PerspectiveCoordinates": null, "AbsoluteCoordinates": {"X": -3.0, "Y": 5.0, "Z": 0.0}}, {"Type": "cwcmod:cwc_blue_rn", "PerspectiveCoordinates": null, "AbsoluteCoordinates": {"X": -2.0, "Y": 5.0, "Z": 0.0}}, {"Type": "cwcmod:cwc_blue_rn", "PerspectiveCoordinates": null, "AbsoluteCoordinates": {"X": -1.0, "Y": 5.0, "Z": 0.0}}, {"Type": "cwcmod:cwc_blue_rn", "PerspectiveCoordinates": null, "AbsoluteCoordinates": {"X": 0.0, "Y": 5.0, "Z": 0.0}}], "BuilderPosition": {"X": -0.9504342696450303, "Y": 3.49422806665524, "Z": -7.029683130689127, "Yaw": -0.5998384, "Pitch": 14.100017}}, {"BuilderInventory": [{"Index": 0, "Type": "cwcmod:cwc_yellow_rn", "Quantity": 20}, {"Index": 1, "Type": "cwcmod:cwc_red_rn", "Quantity": 20}, {"Index": 2, "Type": "cwcmod:cwc_green_rn", "Quantity": 20}, {"Index": 3, "Type": "cwcmod:cwc_orange_rn", "Quantity": 20}, {"Index": 4, "Type": "cwcmod:cwc_purple_rn", "Quantity": 20}, {"Index": 5, "Type": "cwcmod:cwc_blue_rn", "Quantity": 10}], "ChatHistoryTokenized": [["<Builder>", "mission", "has", "started", "."], ["<Builder>", "rip", "me", "lol"], ["<Architect>", "now", "with", "blue", "blocks"], ["<Architect>", "beginning", "from", "the", "middle", "would", "be", "best", "to", "fit", "it", "all", "in"], ["<Architect>", "do", "u", "have", "one", "with", "a", "darker", "shade", "of", "blue", "?"], ["<Builder>", "nope", ":", "-", "("], ["<Architect>", "oh", "stop", "nvm"], ["<Builder>", "lmao"], ["<Architect>", "make", "a", "tower", "of", "5", "purples", "there"], ["<Architect>", "including", "the", "one", "yous", "et"], ["<Builder>", "like", "this"], ["<Architect>", "yes"], ["<Builder>", "good"], ["<Architect>", "now", "on", "one", "of", "the", "4", "sides", "of", "the", "block", "(", "does", "n't", "matter", "which", ")", "put", "four", "blocks", "in", "a", "line"], ["<Architect>", "sorry", ",", "the", "top", "brick"], ["<Architect>", "one", "more", "and", "it", "'ll", "be", "right"], ["<Architect>", "okay", ",", "now", "add", "one", "above", "and", "under", "to", "the", "second", "from", "last", "brick"]], "Timestamp": "2018-04-16 20:40:49", "ScreenshotPath": "207318-Builder-putdown.png", "BlocksInGrid": [{"Type": "cwcmod:cwc_blue_rn", "PerspectiveCoordinates": null, "AbsoluteCoordinates": {"X": 0.0, "Y": 1.0, "Z": 0.0}}, {"Type": "cwcmod:cwc_blue_rn", "PerspectiveCoordinates": null, "AbsoluteCoordinates": {"X": 0.0, "Y": 2.0, "Z": 0.0}}, {"Type": "cwcmod:cwc_blue_rn", "PerspectiveCoordinates": null, "AbsoluteCoordinates": {"X": 0.0, "Y": 3.0, "Z": 0.0}}, {"Type": "cwcmod:cwc_blue_rn", "PerspectiveCoordinates": null, "AbsoluteCoordinates": {"X": -3.0, "Y": 4.0, "Z": 0.0}}, {"Type": "cwcmod:cwc_blue_rn", "PerspectiveCoordinates": null, "AbsoluteCoordinates": {"X": 0.0, "Y": 4.0, "Z": 0.0}}, {"Type": "cwcmod:cwc_blue_rn", "PerspectiveCoordinates": null, "AbsoluteCoordinates": {"X": -4.0, "Y": 5.0, "Z": 0.0}}, {"Type": "cwcmod:cwc_blue_rn", "PerspectiveCoordinates": null, "AbsoluteCoordinates": {"X": -3.0, "Y": 5.0, "Z": 0.0}}, {"Type": "cwcmod:cwc_blue_rn", "PerspectiveCoordinates": null, "AbsoluteCoordinates": {"X": -2.0, "Y": 5.0, "Z": 0.0}}, {"Type": "cwcmod:cwc_blue_rn", "PerspectiveCoordinates": null, "AbsoluteCoordinates": {"X": -1.0, "Y": 5.0, "Z": 0.0}}, {"Type": "cwcmod:cwc_blue_rn", "PerspectiveCoordinates": null, "AbsoluteCoordinates": {"X": 0.0, "Y": 5.0, "Z": 0.0}}], "BuilderPosition": {"X": -3.3160938456801325, "Y": 2.3766351288060883, "Z": -0.3000000119209316, "Yaw": -37.04983, "Pitch": -44.099976}}, {"BuilderInventory": [{"Index": 0, "Type": "cwcmod:cwc_yellow_rn", "Quantity": 20}, {"Index": 1, "Type": "cwcmod:cwc_red_rn", "Quantity": 20}, {"Index": 2, "Type": "cwcmod:cwc_green_rn", "Quantity": 20}, {"Index": 3, "Type": "cwcmod:cwc_orange_rn", "Quantity": 20}, {"Index": 4, "Type": "cwcmod:cwc_purple_rn", "Quantity": 20}, {"Index": 5, "Type": "cwcmod:cwc_blue_rn", "Quantity": 9}], "ChatHistoryTokenized": [["<Builder>", "mission", "has", "started", "."], ["<Builder>", "rip", "me", "lol"], ["<Architect>", "now", "with", "blue", "blocks"], ["<Architect>", "beginning", "from", "the", "middle", "would", "be", "best", "to", "fit", "it", "all", "in"], ["<Architect>", "do", "u", "have", "one", "with", "a", "darker", "shade", "of", "blue", "?"], ["<Builder>", "nope", ":", "-", "("], ["<Architect>", "oh", "stop", "nvm"], ["<Builder>", "lmao"], ["<Architect>", "make", "a", "tower", "of", "5", "purples", "there"], ["<Architect>", "including", "the", "one", "yous", "et"], ["<Builder>", "like", "this"], ["<Architect>", "yes"], ["<Builder>", "good"], ["<Architect>", "now", "on", "one", "of", "the", "4", "sides", "of", "the", "block", "(", "does", "n't", "matter", "which", ")", "put", "four", "blocks", "in", "a", "line"], ["<Architect>", "sorry", ",", "the", "top", "brick"], ["<Architect>", "one", "more", "and", "it", "'ll", "be", "right"], ["<Architect>", "okay", ",", "now", "add", "one", "above", "and", "under", "to", "the", "second", "from", "last", "brick"]], "Timestamp": "2018-04-16 20:40:51", "ScreenshotPath": "211318-Builder-putdown.png", "BlocksInGrid": [{"Type": "cwcmod:cwc_blue_rn", "PerspectiveCoordinates": null, "AbsoluteCoordinates": {"X": 0.0, "Y": 1.0, "Z": 0.0}}, {"Type": "cwcmod:cwc_blue_rn", "PerspectiveCoordinates": null, "AbsoluteCoordinates": {"X": 0.0, "Y": 2.0, "Z": 0.0}}, {"Type": "cwcmod:cwc_blue_rn", "PerspectiveCoordinates": null, "AbsoluteCoordinates": {"X": 0.0, "Y": 3.0, "Z": 0.0}}, {"Type": "cwcmod:cwc_blue_rn", "PerspectiveCoordinates": null, "AbsoluteCoordinates": {"X": -3.0, "Y": 4.0, "Z": 0.0}}, {"Type": "cwcmod:cwc_blue_rn", "PerspectiveCoordinates": null, "AbsoluteCoordinates": {"X": 0.0, "Y": 4.0, "Z": 0.0}}, {"Type": "cwcmod:cwc_blue_rn", "PerspectiveCoordinates": null, "AbsoluteCoordinates": {"X": -4.0, "Y": 5.0, "Z": 0.0}}, {"Type": "cwcmod:cwc_blue_rn", "PerspectiveCoordinates": null, "AbsoluteCoordinates": {"X": -3.0, "Y": 5.0, "Z": 0.0}}, {"Type": "cwcmod:cwc_blue_rn", "PerspectiveCoordinates": null, "AbsoluteCoordinates": {"X": -2.0, "Y": 5.0, "Z": 0.0}}, {"Type": "cwcmod:cwc_blue_rn", "PerspectiveCoordinates": null, "AbsoluteCoordinates": {"X": -1.0, "Y": 5.0, "Z": 0.0}}, {"Type": "cwcmod:cwc_blue_rn", "PerspectiveCoordinates": null, "AbsoluteCoordinates": {"X": 0.0, "Y": 5.0, "Z": 0.0}}, {"Type": "cwcmod:cwc_blue_rn", "PerspectiveCoordinates": null, "AbsoluteCoordinates": {"X": -3.0, "Y": 6.0, "Z": 0.0}}], "BuilderPosition": {"X": -4.368539934337429, "Y": 8.002014225460782, "Z": -1.6787113186701799, "Yaw": -38.699837, "Pitch": 53.85004}}, {"BuilderInventory": [{"Index": 0, "Type": "cwcmod:cwc_yellow_rn", "Quantity": 20}, {"Index": 1, "Type": "cwcmod:cwc_red_rn", "Quantity": 20}, {"Index": 2, "Type": "cwcmod:cwc_green_rn", "Quantity": 20}, {"Index": 3, "Type": "cwcmod:cwc_orange_rn", "Quantity": 20}, {"Index": 4, "Type": "cwcmod:cwc_purple_rn", "Quantity": 20}, {"Index": 5, "Type": "cwcmod:cwc_blue_rn", "Quantity": 9}], "ChatHistoryTokenized": [["<Builder>", "mission", "has", "started", "."], ["<Builder>", "rip", "me", "lol"], ["<Architect>", "now", "with", "blue", "blocks"], ["<Architect>", "beginning", "from", "the", "middle", "would", "be", "best", "to", "fit", "it", "all", "in"], ["<Architect>", "do", "u", "have", "one", "with", "a", "darker", "shade", "of", "blue", "?"], ["<Builder>", "nope", ":", "-", "("], ["<Architect>", "oh", "stop", "nvm"], ["<Builder>", "lmao"], ["<Architect>", "make", "a", "tower", "of", "5", "purples", "there"], ["<Architect>", "including", "the", "one", "yous", "et"], ["<Builder>", "like", "this"], ["<Architect>", "yes"], ["<Builder>", "good"], ["<Architect>", "now", "on", "one", "of", "the", "4", "sides", "of", "the", "block", "(", "does", "n't", "matter", "which", ")", "put", "four", "blocks", "in", "a", "line"], ["<Architect>", "sorry", ",", "the", "top", "brick"], ["<Architect>", "one", "more", "and", "it", "'ll", "be", "right"], ["<Architect>", "okay", ",", "now", "add", "one", "above", "and", "under", "to", "the", "second", "from", "last", "brick"], ["<Builder>", "gorgeous", "lol"]], "Timestamp": "2018-04-16 20:41:01", "ScreenshotPath": "221418-Builder-chat.png", "BlocksInGrid": [{"Type": "cwcmod:cwc_blue_rn", "PerspectiveCoordinates": null, "AbsoluteCoordinates": {"X": 0.0, "Y": 1.0, "Z": 0.0}}, {"Type": "cwcmod:cwc_blue_rn", "PerspectiveCoordinates": null, "AbsoluteCoordinates": {"X": 0.0, "Y": 2.0, "Z": 0.0}}, {"Type": "cwcmod:cwc_blue_rn", "PerspectiveCoordinates": null, "AbsoluteCoordinates": {"X": 0.0, "Y": 3.0, "Z": 0.0}}, {"Type": "cwcmod:cwc_blue_rn", "PerspectiveCoordinates": null, "AbsoluteCoordinates": {"X": -3.0, "Y": 4.0, "Z": 0.0}}, {"Type": "cwcmod:cwc_blue_rn", "PerspectiveCoordinates": null, "AbsoluteCoordinates": {"X": 0.0, "Y": 4.0, "Z": 0.0}}, {"Type": "cwcmod:cwc_blue_rn", "PerspectiveCoordinates": null, "AbsoluteCoordinates": {"X": -4.0, "Y": 5.0, "Z": 0.0}}, {"Type": "cwcmod:cwc_blue_rn", "PerspectiveCoordinates": null, "AbsoluteCoordinates": {"X": -3.0, "Y": 5.0, "Z": 0.0}}, {"Type": "cwcmod:cwc_blue_rn", "PerspectiveCoordinates": null, "AbsoluteCoordinates": {"X": -2.0, "Y": 5.0, "Z": 0.0}}, {"Type": "cwcmod:cwc_blue_rn", "PerspectiveCoordinates": null, "AbsoluteCoordinates": {"X": -1.0, "Y": 5.0, "Z": 0.0}}, {"Type": "cwcmod:cwc_blue_rn", "PerspectiveCoordinates": null, "AbsoluteCoordinates": {"X": 0.0, "Y": 5.0, "Z": 0.0}}, {"Type": "cwcmod:cwc_blue_rn", "PerspectiveCoordinates": null, "AbsoluteCoordinates": {"X": -3.0, "Y": 6.0, "Z": 0.0}}], "BuilderPosition": {"X": -1.2110102868368857, "Y": 4.2636922789990415, "Z": -6.595104881327993, "Yaw": 1.6501608, "Pitch": 10.200041}}]}